LICENSE
MANIFEST.in
README.md
pyproject.toml
setup.py
config/config.yaml
splat/__init__.py
splat/__main__.py
splat/splat.py
splat_workflow.egg-info/PKG-INFO
splat_workflow.egg-info/SOURCES.txt
splat_workflow.egg-info/dependency_links.txt
splat_workflow.egg-info/entry_points.txt
splat_workflow.egg-info/requires.txt
splat_workflow.egg-info/top_level.txt
tests/data/.DS_Store
tests/data/riana_fit_peptides.csv
tests/data/time16_tmt/.DS_Store
tests/data/time16_tmt/tmt_out.txt
tests/data/time8_tmt/.DS_Store
tests/data/time8_tmt/tmt_out.txt
workflow/Snakefile