Metadata-Version: 2.1
Name: splat-workflow
Version: 0.1.0
Summary: simultaneous proteome localization and turnover
Home-page: https://github.com/lau-lab/splat
Author: Edward Lau
Author-email: edward.lau@cuanschutz.edu
License: UNKNOWN
Project-URL: Source, https://github.com/lau-lab/splat
Project-URL: Edward Lau Lab, https://www.laulab.net
Keywords: scientific turnover kinetics proteomics mass-spectrometry
Platform: UNKNOWN
Classifier: Development Status :: 3 - Alpha
Classifier: Intended Audience :: Developers
Classifier: Topic :: Software Development :: Build Tools
Classifier: License :: OSI Approved :: MIT License
Classifier: Programming Language :: Python :: 3.7
Classifier: Programming Language :: Python :: 3.8
Classifier: Programming Language :: Python :: 3 :: Only
Requires-Python: >=3.6, <4
License-File: LICENSE
